Metadata-Version: 2.4
Name: strkit
Version: 0.24.2
Summary: A toolkit for analyzing variation in short(ish) tandem repeats.
Home-page: https://github.com/davidlougheed/strkit
Author: David Lougheed
Author-email: david.lougheed@gmail.com
License: GPLv3
Classifier: Programming Language :: Python :: 3.10
Classifier: Programming Language :: Python :: 3.11
Classifier: Programming Language :: Python :: 3.12
Classifier: Programming Language :: Python :: 3.13
Classifier: Programming Language :: Python :: 3 :: Only
Classifier: License :: OSI Approved :: GNU General Public License v3 (GPLv3)
Classifier: Operating System :: POSIX
Classifier: Operating System :: POSIX :: Linux
Classifier: Operating System :: MacOS :: MacOS X
Requires-Python: ~=3.10
License-File: LICENSE
Requires-Dist: Flask<3.2,>=2.2.5
Requires-Dist: orjson<4,>=3.9.15
Requires-Dist: pysam<0.24,>=0.19
Requires-Dist: numpy<1.27,>=1.23.4
Requires-Dist: parasail<1.4,>=1.2.4
Requires-Dist: pydantic<3,>=2.11.7
Requires-Dist: scikit-learn<1.8,>=1.2.1
Requires-Dist: scipy<1.17,>=1.10
Requires-Dist: statsmodels<0.15,>=0.14.0
Requires-Dist: strkit_rust_ext==0.24.2
Dynamic: author
Dynamic: author-email
Dynamic: classifier
Dynamic: description
Dynamic: description-content-type
Dynamic: home-page
Dynamic: license
Dynamic: license-file
Dynamic: requires-dist
Dynamic: requires-python
Dynamic: summary
